nanonispy2/__init__.py
nanonispy2/constants.py
nanonispy2/read.py
nanonispy2-1.2.0.dist-info/LICENSE
nanonispy2-1.2.0.dist-info/METADATA
nanonispy2-1.2.0.dist-info/WHEEL
nanonispy2-1.2.0.dist-info/top_level.txt
nanonispy2-1.2.0.dist-info/RECORD
