Metadata-Version: 2.1
Name: nanonispy2
Version: 1.2.0
Summary: Library to parse Nanonis files. Forked from https://github.com/underchemist/nanonispy
Home-page: https://github.com/ceds92/nanonispy2
Author: Julian Ceddia
Author-email: jdceddia@gmail.com
License: MIT
Keywords: science numpy parse library
Platform: any
Classifier: Development Status :: 4 - Beta
Classifier: Intended Audience :: Science/Research
Classifier: Topic :: Scientific/Engineering :: Physics
Classifier: License :: OSI Approved :: MIT License
Classifier: Programming Language :: Python :: 3.6
Classifier: Programming Language :: Python :: 3.7
Classifier: Programming Language :: Python :: 3.8
Classifier: Programming Language :: Python :: 3.9
Requires-Python: >=3.6
License-File: LICENSE
Requires-Dist: numpy
